momba/__init__.py
momba/metadata.py
momba/py.typed
momba/analysis/__init__.py
momba/analysis/checkers.py
momba/debug/__init__.py
momba/debug/memory.py
momba/engine/__init__.py
momba/engine/__main__.py
momba/engine/_engine.py
momba/engine/explore.py
momba/engine/objectives.py
momba/engine/time.py
momba/engine/translator.py
momba/engine/values.py
momba/engine/zones.py
momba/gym/__init__.py
momba/gym/abstract.py
momba/gym/checker.py
momba/gym/dump_nn.py
momba/gym/env.py
momba/gym/generic.py
momba/jani/__init__.py
momba/jani/dump_model.py
momba/jani/jsonutils.py
momba/jani/load_model.py
momba/kit/__init__.py
momba/kit/dbm.py
momba/kit/intervals.py
momba/model/__init__.py
momba/model/actions.py
momba/model/automata.py
momba/model/context.py
momba/model/distributions.py
momba/model/errors.py
momba/model/expressions.py
momba/model/functions.py
momba/model/networks.py
momba/model/observations.py
momba/model/operators.py
momba/model/properties.py
momba/model/types.py
momba/moml/__init__.py
momba/moml/__main__.py
momba/moml/lexer.py
momba/moml/parser.py
momba/tools/__init__.py
momba/tools/errors.py
momba/tools/modest.py
momba/tools/storm.py
momba/tools/storm_docker.py
momba/utils/__init__.py
momba/utils/cache.py
momba/utils/checks.py
momba/utils/clstools.py
momba/utils/distribution.py
momba-0.6.12.dist-info/METADATA
momba-0.6.12.dist-info/WHEEL
momba-0.6.12.dist-info/entry_points.txt
momba-0.6.12.dist-info/licenses/LICENSE-APACHE
momba-0.6.12.dist-info/licenses/LICENSE-MIT
momba-0.6.12.dist-info/RECORD
