Metadata-Version: 2.3
Name: momba
Version: 0.6.12
Summary: A Python library for quantitative models.
Project-URL: repository, https://github.com/koehlma/momba.git
Project-URL: homepage, https://momba.dev/
Author-email: Maximilian Köhl <koehl@cs.uni-saarland.de>
License: MIT License
License-File: LICENSE-APACHE
License-File: LICENSE-MIT
Classifier: Development Status :: 4 - Beta
Classifier: License :: OSI Approved :: Apache Software License
Classifier: License :: OSI Approved :: MIT License
Classifier: Operating System :: OS Independent
Requires-Python: >=3.9
Requires-Dist: immutables>=0.20
Requires-Dist: momba-engine==0.6.12
Requires-Dist: mxu>=0.0.6
Provides-Extra: all
Requires-Dist: click>=8.1.7; extra == 'all'
Requires-Dist: docker>=7.1.0; extra == 'all'
Requires-Dist: gymnasium>=0.29.1; extra == 'all'
Requires-Dist: torch>=2.4.0; extra == 'all'
Provides-Extra: cli
Requires-Dist: click>=8.1.7; extra == 'cli'
Provides-Extra: docker
Requires-Dist: docker>=7.1.0; extra == 'docker'
Provides-Extra: engine
Provides-Extra: gym
Requires-Dist: gymnasium>=0.29.1; extra == 'gym'
Requires-Dist: torch>=2.4.0; extra == 'gym'
